{
  "type": "FeatureCollection",
  "features": [
    {
      "type": "Feature",
      "properties": {
        "stroke": "#555555",
        "stroke-width": 2,
        "stroke-opacity": 1,
        "fill": "#555555",
        "fill-opacity": 0.5,
        "rowid_": "cfbeec0a-a935-490f-b261-2566c06d2198"
      },
      "geometry": {
        "type": "Polygon",
        "coordinates": [
          [
            [
              144.76866960525513,
              -37.88325612619047
            ],
            [
              144.7690786421299,
              -37.883252950735624
            ],
            [
              144.7690813243389,
              -37.88320320192508
            ],
            [
              144.76867094635963,
              -37.88320637738207
            ],
            [
              144.76866960525513,
              -37.88325612619047
            ]
          ]
        ]
      }
    },
    {
      "type": "Feature",
      "properties": {
        "stroke": "#555555",
        "stroke-width": 2,
        "stroke-opacity": 1,
        "fill": "#555555",
        "fill-opacity": 0.5,
        "rowid_": "55292e0f-b4ba-4a34-ab33-52ebedba7bac"
      },
      "geometry": {
        "type": "Polygon",
        "coordinates": [
          [
            [
              144.77155297994614,
              -37.88395260597933
            ],
            [
              144.77161198854446,
              -37.88397589242383
            ],
            [
              144.77308720350266,
              -37.884765510228874
            ],
            [
              144.7731649875641,
              -37.884668131547066
            ],
            [
              144.77152884006497,
              -37.88375361242608
            ],
            [
              144.77155297994614,
              -37.88395260597933
            ]
          ]
        ]
      }
    },
    {
      "type": "Feature",
      "properties": {
        "stroke": "#555555",
        "stroke-width": 2,
        "stroke-opacity": 1,
        "fill": "#555555",
        "fill-opacity": 0.5,
        "rowid_": "0040d68b-decb-43e2-b6ea-85b9c630ce93"
      },
      "geometry": {
        "type": "Polygon",
        "coordinates": [
          [
            [
              144.77032586932182,
              -37.88331751829068
            ],
            [
              144.77047875523567,
              -37.88337467640694
            ],
            [
              144.77050021290776,
              -37.883336571001024
            ],
            [
              144.77035135030746,
              -37.883279412855195
            ],
            [
              144.77032586932182,
              -37.88331751829068
            ]
          ]
        ]
      }
    },
    {
      "type": "Feature",
      "properties": {
        "stroke": "#555555",
        "stroke-width": 2,
        "stroke-opacity": 1,
        "fill": "#555555",
        "fill-opacity": 0.5,
        "rowid_": "49189e22-cd2e-49dc-8474-c2ed66dbbd4e"
      },
      "geometry": {
        "type": "Polygon",
        "coordinates": [
          [
            [
              144.76004898548126,
              -37.87465225817387
            ],
            [
              144.75992560386655,
              -37.87466284425889
            ],
            [
              144.75992560386655,
              -37.874791994373744
            ],
            [
              144.76012408733365,
              -37.87478564273406
            ],
            [
              144.76031184196472,
              -37.874756001741545
            ],
            [
              144.7605586051941,
              -37.87470518858379
            ],
            [
              144.7605264186859,
              -37.87458027275533
            ],
            [
              144.76032257080078,
              -37.87461838269155
            ],
            [
              144.7601455450058,
              -37.87464378930475
            ],
            [
              144.76004898548126,
              -37.87465225817387
            ]
          ]
        ]
      }
    },
    {
      "type": "Feature",
      "properties": {
        "stroke": "#555555",
        "stroke-width": 2,
        "stroke-opacity": 1,
        "fill": "#555555",
        "fill-opacity": 0.5,
        "rowid_": "13b0515d-570d-4e51-8e98-474fe1785fb1"
      },
      "geometry": {
        "type": "Polygon",
        "coordinates": [
          [
            [
              144.7559666633606,
              -37.87335227536899
            ],
            [
              144.75596129894257,
              -37.873451786264184
            ],
            [
              144.75622415542603,
              -37.873470841526654
            ],
            [
              144.75623220205307,
              -37.873373447911135
            ],
            [
              144.7559666633606,
              -37.87335227536899
            ]
          ]
        ]
      }
    },
    {
      "type": "Feature",
      "properties": {
        "stroke": "#555555",
        "stroke-width": 2,
        "stroke-opacity": 1,
        "fill": "#555555",
        "fill-opacity": 0.5,
        "rowid_": "92370ddc-b801-46aa-ad45-ef010e88af3f"
      },
      "geometry": {
        "type": "Polygon",
        "coordinates": [
          [
            [
              144.76609468460083,
              -37.877106071990305
            ],
            [
              144.7660195827484,
              -37.8773093177866
            ],
            [
              144.76620733737943,
              -37.877360129148045
            ],
            [
              144.7663950920105,
              -37.87741094047444
            ],
            [
              144.7663950920105,
              -37.87720769495855
            ],
            [
              144.76609468460083,
              -37.877106071990305
            ]
          ]
        ]
      }
    },
    {
      "type": "Feature",
      "properties": {
        "stroke": "#555555",
        "stroke-width": 2,
        "stroke-opacity": 1,
        "fill": "#555555",
        "fill-opacity": 0.5,
        "rowid_": "8c237d2e-2e57-4a35-b12b-9861fae8c9fc"
      },
      "geometry": {
        "type": "Polygon",
        "coordinates": [
          [
            [
              144.75565552711484,
              -37.87432197155683
            ],
            [
              144.7556635737419,
              -37.874381253879186
            ],
            [
              144.75599884986877,
              -37.87423304798385
            ],
            [
              144.7563475370407,
              -37.87412930367971
            ],
            [
              144.75631803274155,
              -37.87407849008968
            ],
            [
              144.756041765213,
              -37.87414624153526
            ],
            [
              144.75565552711484,
              -37.87432197155683
            ]
          ]
        ]
      }
    },
    {
      "type": "Feature",
      "properties": {
        "stroke": "#555555",
        "stroke-width": 2,
        "stroke-opacity": 1,
        "fill": "#555555",
        "fill-opacity": 0.5,
        "rowid_": "c3346d72-ef6f-4ba0-afdd-ad315e0254fc"
      },
      "geometry": {
        "type": "Polygon",
        "coordinates": [
          [
            [
              144.75563943386078,
              -37.87428174423949
            ],
            [
              144.75565552711484,
              -37.87431773710341
            ],
            [
              144.75603640079498,
              -37.87414412430353
            ],
            [
              144.75631266832352,
              -37.87407849008968
            ],
            [
              144.7562912106514,
              -37.874042497108874
            ],
            [
              144.7560203075409,
              -37.87411236582026
            ],
            [
              144.75563943386078,
              -37.87428174423949
            ]
          ]
        ]
      }
    },
    {
      "type": "Feature",
      "properties": {},
      "geometry": {
        "type": "Point",
        "coordinates": [
          144.77171391248703,
          -37.88394413817951
        ]
      }
    },
    {
      "type": "Feature",
      "properties": {},
      "geometry": {
        "type": "Point",
        "coordinates": [
          144.77181047201154,
          -37.884016114446965
        ]
      }
    },
    {
      "type": "Feature",
      "properties": {},
      "geometry": {
        "type": "Point",
        "coordinates": [
          144.77221816778183,
          -37.88423839365238
        ]
      }
    },
    {
      "type": "Feature",
      "properties": {},
      "geometry": {
        "type": "Point",
        "coordinates": [
          144.77199018001556,
          -37.88410502620964
        ]
      }
    },
    {
      "type": "Feature",
      "properties": {},
      "geometry": {
        "type": "Point",
        "coordinates": [
          144.7724086046219,
          -37.88434635759578
        ]
      }
    },
    {
      "type": "Feature",
      "properties": {},
      "geometry": {
        "type": "Point",
        "coordinates": [
          144.77159321308136,
          -37.88390603306826
        ]
      }
    },
    {
      "type": "Feature",
      "properties": {},
      "geometry": {
        "type": "Polygon",
        "coordinates": [
          [
            [
              144.76547241210938,
              -37.87879976982364
            ],
            [
              144.7658371925354,
              -37.878935263967875
            ],
            [
              144.76603031158447,
              -37.87846103337257
            ],
            [
              144.76626634597778,
              -37.87798679972396
            ],
            [
              144.7658371925354,
              -37.877868240834744
            ],
            [
              144.76547241210938,
              -37.87879976982364
            ]
          ]
        ]
      }
    },
    {
      "type": "Feature",
      "properties": {},
      "geometry": {
        "type": "Polygon",
        "coordinates": [
          [
            [
              144.7658720612526,
              -37.8788526972534
            ],
            [
              144.76608127355578,
              -37.87851396104573
            ],
            [
              144.76622611284256,
              -37.87822603404441
            ],
            [
              144.76624757051468,
              -37.87810324130443
            ],
            [
              144.76624757051468,
              -37.87802279077758
            ],
            [
              144.766118824482,
              -37.878302250124875
            ],
            [
              144.76600080728534,
              -37.87853089789312
            ],
            [
              144.7658720612526,
              -37.8788526972534
            ]
          ]
        ]
      }
    },
    {
      "type": "Feature",
      "properties": {},
      "geometry": {
        "type": "Point",
        "coordinates": [
          144.76631999015808,
          -37.877360129148045
        ]
      }
    },
    {
      "type": "Feature",
      "properties": {},
      "geometry": {
        "type": "Point",
        "coordinates": [
          144.76620733737943,
          -37.8773389577517
        ]
      }
    },
    {
      "type": "Feature",
      "properties": {},
      "geometry": {
        "type": "Point",
        "coordinates": [
          144.76608932018277,
          -37.87731355206806
        ]
      }
    },
    {
      "type": "Feature",
      "properties": {},
      "geometry": {
        "type": "Point",
        "coordinates": [
          144.76578891277313,
          -37.878634635998345
        ]
      }
    },
    {
      "type": "Feature",
      "properties": {},
      "geometry": {
        "type": "Polygon",
        "coordinates": [
          [
            [
              144.7172650694847,
              -37.86848454642575
            ],
            [
              144.7177666425705,
              -37.86858194650415
            ],
            [
              144.7180938720703,
              -37.86857135954534
            ],
            [
              144.71809923648834,
              -37.868533246481036
            ],
            [
              144.7179839015007,
              -37.86854171605259
            ],
            [
              144.71777200698853,
              -37.868550185623164
            ],
            [
              144.71757888793945,
              -37.86851630733502
            ],
            [
              144.71727311611176,
              -37.86844643331654
            ],
            [
              144.7172650694847,
              -37.86848454642575
            ]
          ]
        ]
      }
    },
    {
      "type": "Feature",
      "properties": {},
      "geometry": {
        "type": "Polygon",
        "coordinates": [
          [
            [
              144.71810191869736,
              -37.86856712476139
            ],
            [
              144.71896827220917,
              -37.868539598659794
            ],
            [
              144.7189736366272,
              -37.86849936818511
            ],
            [
              144.71881538629532,
              -37.86850360297296
            ],
            [
              144.71849083900452,
              -37.86851842472849
            ],
            [
              144.71810460090637,
              -37.868531129088
            ],
            [
              144.71810191869736,
              -37.86856712476139
            ]
          ]
        ]
      }
    },
    {
      "type": "Feature",
      "properties": {},
      "geometry": {
        "type": "Polygon",
        "coordinates": [
          [
            [
              144.71726238727567,
              -37.86850148557906
            ],
            [
              144.71775323152542,
              -37.86860523780817
            ],
            [
              144.7180938720703,
              -37.868584063895725
            ],
            [
              144.71896559000015,
              -37.86855442040809
            ],
            [
              144.71897095441818,
              -37.86853748126694
            ],
            [
              144.7180938720703,
              -37.8685692421534
            ],
            [
              144.71776396036148,
              -37.868584063895725
            ],
            [
              144.71727043390274,
              -37.868488781214445
            ],
            [
              144.71726238727567,
              -37.86850148557906
            ]
          ]
        ]
      }
    },
    {
      "type": "Feature",
      "properties": {},
      "geometry": {
        "type": "Polygon",
        "coordinates": [
          [
            [
              144.71810191869736,
              -37.868584063895725
            ],
            [
              144.71809923648834,
              -37.86859676824392
            ],
            [
              144.71896022558212,
              -37.86857135954534
            ],
            [
              144.71896290779114,
              -37.86855442040809
            ],
            [
              144.71810191869736,
              -37.868584063895725
            ]
          ]
        ]
      }
    },
    {
      "type": "Feature",
      "properties": {},
      "geometry": {
        "type": "Point",
        "coordinates": [
          144.71879661083221,
          -37.868509955154266
        ]
      }
    },
    {
      "type": "Feature",
      "properties": {},
      "geometry": {
        "type": "Point",
        "coordinates": [
          144.7186705470085,
          -37.86851207254791
        ]
      }
    },
    {
      "type": "Feature",
      "properties": {},
      "geometry": {
        "type": "Point",
        "coordinates": [
          144.71852838993073,
          -37.8685205421219
        ]
      }
    },
    {
      "type": "Feature",
      "properties": {},
      "geometry": {
        "type": "Point",
        "coordinates": [
          144.7183808684349,
          -37.8685205421219
        ]
      }
    },
    {
      "type": "Feature",
      "properties": {},
      "geometry": {
        "type": "Point",
        "coordinates": [
          144.71826553344727,
          -37.8685290116949
        ]
      }
    },
    {
      "type": "Feature",
      "properties": {},
      "geometry": {
        "type": "Point",
        "coordinates": [
          144.718936085701,
          -37.868507837760546
        ]
      }
    },
    {
      "type": "Feature",
      "properties": {},
      "geometry": {
        "type": "Point",
        "coordinates": [
          144.71815824508667,
          -37.86852689430174
        ]
      }
    },
    {
      "type": "Feature",
      "properties": {},
      "geometry": {
        "type": "Point",
        "coordinates": [
          144.7180026769638,
          -37.868545950838
        ]
      }
    },
    {
      "type": "Feature",
      "properties": {},
      "geometry": {
        "type": "Point",
        "coordinates": [
          144.7178417444229,
          -37.86854806823061
        ]
      }
    },
    {
      "type": "Feature",
      "properties": {},
      "geometry": {
        "type": "Point",
        "coordinates": [
          144.71770763397217,
          -37.86854171605259
        ]
      }
    },
    {
      "type": "Feature",
      "properties": {},
      "geometry": {
        "type": "Point",
        "coordinates": [
          144.71755474805832,
          -37.8685141899415
        ]
      }
    },
    {
      "type": "Feature",
      "properties": {},
      "geometry": {
        "type": "Point",
        "coordinates": [
          144.71743673086166,
          -37.86849513339703
        ]
      }
    },
    {
      "type": "Feature",
      "properties": {},
      "geometry": {
        "type": "Point",
        "coordinates": [
          144.71731334924698,
          -37.8684697246634
        ]
      }
    },
    {
      "type": "Feature",
      "properties": {},
      "geometry": {
        "type": "Point",
        "coordinates": [
          144.7187376022339,
          -37.868545950838
        ]
      }
    },
    {
      "type": "Feature",
      "properties": {},
      "geometry": {
        "type": "Point",
        "coordinates": [
          144.7183245420456,
          -37.86856077258502
        ]
      }
    },
    {
      "type": "Feature",
      "properties": {},
      "geometry": {
        "type": "Point",
        "coordinates": [
          144.71778005361557,
          -37.86859465085271
        ]
      }
    },
    {
      "type": "Feature",
      "properties": {},
      "geometry": {
        "type": "Point",
        "coordinates": [
          144.71736431121826,
          -37.8685141899415
        ]
      }
    },
    {
      "type": "Feature",
      "properties": {},
      "geometry": {
        "type": "Point",
        "coordinates": [
          144.71861690282822,
          -37.86857135954534
        ]
      }
    },
    {
      "type": "Feature",
      "properties": {},
      "geometry": {
        "type": "Point",
        "coordinates": [
          144.7558781504631,
          -37.87427962701166
        ]
      }
    },
    {
      "type": "Feature",
      "properties": {},
      "geometry": {
        "type": "Point",
        "coordinates": [
          144.75602835416794,
          -37.87415259323009
        ]
      }
    },
    {
      "type": "Feature",
      "properties": {},
      "geometry": {
        "type": "Point",
        "coordinates": [
          144.75610077381134,
          -37.873396737700475
        ]
      }
    },
    {
      "type": "Feature",
      "properties": {},
      "geometry": {
        "type": "Point",
        "coordinates": [
          144.75601226091385,
          -37.87339038594047
        ]
      }
    },
    {
      "type": "Feature",
      "properties": {
        "marker-color": "#7e7e7e",
        "marker-size": "medium",
        "marker-symbol": ""
      },
      "geometry": {
        "type": "Point",
        "coordinates": [
          144.75997388362885,
          -37.874785642734054
        ]
      }
    },
    {
      "type": "Feature",
      "properties": {},
      "geometry": {
        "type": "Point",
        "coordinates": [
          144.76010262966156,
          -37.87477082223929
        ]
      }
    },
    {
      "type": "Feature",
      "properties": {},
      "geometry": {
        "type": "Point",
        "coordinates": [
          144.7602179646492,
          -37.87475176731308
        ]
      }
    },
    {
      "type": "Feature",
      "properties": {},
      "geometry": {
        "type": "Point",
        "coordinates": [
          144.76035743951797,
          -37.87473482959674
        ]
      }
    },
    {
      "type": "Feature",
      "properties": {},
      "geometry": {
        "type": "Point",
        "coordinates": [
          144.7561812400818,
          -37.87340308945992
        ]
      }
    },
    {
      "type": "Feature",
      "properties": {},
      "geometry": {
        "type": "Point",
        "coordinates": [
          144.7687017917633,
          -37.88322860557721
        ]
      }
    },
    {
      "type": "Feature",
      "properties": {},
      "geometry": {
        "type": "Point",
        "coordinates": [
          144.768825173378,
          -37.88322860557721
        ]
      }
    },
    {
      "type": "Feature",
      "properties": {},
      "geometry": {
        "type": "Point",
        "coordinates": [
          144.7703379392624,
          -37.88329211466921
        ]
      }
    },
    {
      "type": "Feature",
      "properties": {},
      "geometry": {
        "type": "Point",
        "coordinates": [
          144.7704291343689,
          -37.88331751829068
        ]
      }
    },
    {
      "type": "Feature",
      "properties": {},
      "geometry": {
        "type": "Polygon",
        "coordinates": [
          [
            [
              144.76448267698288,
              -37.878816706605306
            ],
            [
              144.76470798254013,
              -37.87888868788392
            ],
            [
              144.7648474574089,
              -37.87855418605191
            ],
            [
              144.7646114230156,
              -37.87848643866045
            ],
            [
              144.76448267698288,
              -37.878816706605306
            ]
          ]
        ]
      }
    },
    {
      "type": "Feature",
      "properties": {
        "marker-color": "#7e7e7e",
        "marker-size": "medium",
        "marker-symbol": ""
      },
      "geometry": {
        "type": "Point",
        "coordinates": [
          144.7646141052246,
          -37.87882517499467
        ]
      }
    },
    {
      "type": "Feature",
      "properties": {
        "stroke": "#555555",
        "stroke-width": 2,
        "stroke-opacity": 1,
        "fill": "#555555",
        "fill-opacity": 0.5
      },
      "geometry": {
        "type": "Polygon",
        "coordinates": [
          [
            [
              144.7171202301979,
              -37.868509955154266
            ],
            [
              144.71786856651306,
              -37.86868781600855
            ],
            [
              144.7188341617584,
              -37.86867087689807
            ],
            [
              144.7192633152008,
              -37.868679346453796
            ],
            [
              144.71988558769226,
              -37.86866240734137
            ],
            [
              144.72040057182312,
              -37.86869628556233
            ],
            [
              144.72091555595398,
              -37.869001188850056
            ],
            [
              144.72119450569153,
              -37.869331499321284
            ],
            [
              144.72157001495358,
              -37.86980578869032
            ],
            [
              144.72179532051086,
              -37.87044099288413
            ],
            [
              144.7219455242157,
              -37.871321800304315
            ],
            [
              144.7217845916748,
              -37.8718130152533
            ],
            [
              144.72163438796997,
              -37.872177189739304
            ],
            [
              144.72158074378967,
              -37.87279543532598
            ],
            [
              144.7218382358551,
              -37.87324429530937
            ],
            [
              144.72179532051086,
              -37.87356611776507
            ],
            [
              144.7216773033142,
              -37.873921814633114
            ],
            [
              144.72161293029782,
              -37.874523107814035
            ],
            [
              144.72166657447815,
              -37.875369991293894
            ],
            [
              144.72163438796997,
              -37.87601361622714
            ],
            [
              144.72168803215027,
              -37.87675039049737
            ],
            [
              144.72184896469116,
              -37.877825898328055
            ],
            [
              144.7218918800354,
              -37.87825779075419
            ],
            [
              144.72203135490417,
              -37.87874049105716
            ],
            [
              144.72232103347778,
              -37.87913003636354
            ],
            [
              144.72264289855957,
              -37.87961273095031
            ],
            [
              144.72305059432983,
              -37.87987524773087
            ],
            [
              144.72349047660828,
              -37.8799768668786
            ],
            [
              144.7243058681488,
              -37.87990912079569
            ],
            [
              144.72494959831238,
              -37.87969741388498
            ],
            [
              144.72553968429565,
              -37.879460301422554
            ],
            [
              144.72612977027893,
              -37.879324808244164
            ],
            [
              144.72667694091797,
              -37.879290934910614
            ],
            [
              144.72742795944214,
              -37.87947723805233
            ],
            [
              144.72813606262207,
              -37.8795111113002
            ],
            [
              144.72867250442505,
              -37.87912156800922
            ],
            [
              144.7288978099823,
              -37.878240853844005
            ],
            [
              144.72897291183472,
              -37.87774121324166
            ],
            [
              144.7291338443756,
              -37.8773093177866
            ],
            [
              144.72931623458862,
              -37.87685201395632
            ],
            [
              144.72962737083432,
              -37.87658948640065
            ],
            [
              144.72989559173584,
              -37.8765640804585
            ],
            [
              144.73061442375183,
              -37.87674192186946
            ],
            [
              144.73161220550537,
              -37.87704679186075
            ],
            [
              144.73249197006226,
              -37.87716535207216
            ],
            [
              144.73339319229126,
              -37.87700444888186
            ],
            [
              144.7344446182251,
              -37.87682660810473
            ],
            [
              144.73517417907715,
              -37.876724984610725
            ],
            [
              144.7361183166504,
              -37.87663182961807
            ],
            [
              144.73689079284668,
              -37.87668264144685
            ],
            [
              144.73751306533813,
              -37.876724984610725
            ],
            [
              144.73823189735413,
              -37.87682660810473
            ],
            [
              144.7387683391571,
              -37.876843545340094
            ],
            [
              144.73918676376343,
              -37.87644551927933
            ],
            [
              144.73939061164856,
              -37.87601361622714
            ],
            [
              144.73969101905823,
              -37.875471616657215
            ],
            [
              144.74007725715637,
              -37.87541233521231
            ],
            [
              144.74058151245117,
              -37.87559017940389
            ],
            [
              144.74101066589355,
              -37.8757002732121
            ],
            [
              144.74132180213928,
              -37.87571721070645
            ],
            [
              144.74207282066345,
              -37.875369991293894
            ],
            [
              144.74280238151547,
              -37.87498889493278
            ],
            [
              144.74425077438354,
              -37.874294447605244
            ],
            [
              144.74473357200623,
              -37.874226696295956
            ],
            [
              144.74530220031735,
              -37.87436219885221
            ],
            [
              144.74597811698914,
              -37.87469248528888
            ],
            [
              144.7467291355133,
              -37.87496348843861
            ],
            [
              144.74778056144714,
              -37.87494655077096
            ],
            [
              144.74868178367615,
              -37.87466707869248
            ],
            [
              144.74910020828247,
              -37.87461626547339
            ],
            [
              144.74945425987244,
              -37.87466707869248
            ],
            [
              144.75008726119995,
              -37.87475176731308
            ],
            [
              144.75062370300293,
              -37.87507358318341
            ],
            [
              144.75173950195312,
              -37.875768023166124
            ],
            [
              144.7523295879364,
              -37.87604749106786
            ],
            [
              144.75279092788696,
              -37.87620839634849
            ],
            [
              144.75369215011597,
              -37.876242271099635
            ],
            [
              144.75431442260742,
              -37.87603902235913
            ],
            [
              144.75496888160703,
              -37.875437741551686
            ],
            [
              144.75571990013123,
              -37.874827986988365
            ],
            [
              144.75632071495056,
              -37.8745908588507
            ],
            [
              144.75693225860596,
              -37.874438418930566
            ],
            [
              144.7574687004089,
              -37.87421822737792
            ],
            [
              144.75786566734314,
              -37.87423516521303
            ],
            [
              144.75829482078552,
              -37.87441301224654
            ],
            [
              144.75878834724426,
              -37.87465860982506
            ],
            [
              144.75928187370297,
              -37.87476870502551
            ],
            [
              144.75996851921082,
              -37.87484492468328
            ],
            [
              144.7605264186859,
              -37.87474329845539
            ],
            [
              144.7611916065216,
              -37.87434526104631
            ],
            [
              144.76165294647217,
              -37.873998035167126
            ],
            [
              144.76213574409485,
              -37.87363386968187
            ],
            [
              144.76256489753723,
              -37.87342214473499
            ],
            [
              144.7629189491272,
              -37.87337133065719
            ],
            [
              144.76328372955322,
              -37.87360846272038
            ],
            [
              144.76370215415955,
              -37.87410813135479
            ],
            [
              144.76404547691345,
              -37.87460779660013
            ],
            [
              144.764324426651,
              -37.8750058325907
            ],
            [
              144.76458191871643,
              -37.875480085431164
            ],
            [
              144.76479649543762,
              -37.87603902235913
            ],
            [
              144.76487159729004,
              -37.87661489233402
            ],
            [
              144.76486086845398,
              -37.8770721976364
            ],
            [
              144.7647213935852,
              -37.87779202430518
            ],
            [
              144.76435661315915,
              -37.878401754333474
            ],
            [
              144.76404547691345,
              -37.878986074207695
            ],
            [
              144.76384162902832,
              -37.87964660413587
            ],
            [
              144.76380944252014,
              -37.88018857298604
            ],
            [
              144.76380944252014,
              -37.88072206967788
            ],
            [
              144.7640025615692,
              -37.88106926386183
            ],
            [
              144.7641634941101,
              -37.88149266918818
            ],
            [
              144.76424932479858,
              -37.88199228434249
            ],
            [
              144.76436734199524,
              -37.88219551665583
            ],
            [
              144.76476430892944,
              -37.882525767968865
            ],
            [
              144.76512908935547,
              -37.882889889494884
            ],
            [
              144.76547241210938,
              -37.88330481648104
            ],
            [
              144.76581573486328,
              -37.88399071106649
            ],
            [
              144.7660195827484,
              -37.884549583412806
            ],
            [
              144.76629853248596,
              -37.88478667949049
            ],
            [
              144.76728558540344,
              -37.885167725158915
            ],
            [
              144.76810097694394,
              -37.88533707815643
            ],
            [
              144.7689163684845,
              -37.88556570408527
            ],
            [
              144.76975321769712,
              -37.885057645501675
            ],
            [
              144.77031111717224,
              -37.88496450104778
            ],
            [
              144.77075099945068,
              -37.88509151618296
            ],
            [
              144.77131962776184,
              -37.885370948709195
            ],
            [
              144.7723388671875,
              -37.885455625022956
            ],
            [
              144.77285385131836,
              -37.88554876885563
            ],
            [
              144.77304697036743,
              -37.8858705375529
            ],
            [
              144.7732400894165,
              -37.88656487574066
            ],
            [
              144.7736155986786,
              -37.88727614221754
            ],
            [
              144.77454900741574,
              -37.887809587566466
            ],
            [
              144.7746777534485,
              -37.88802973848865
            ],
            [
              144.7749137878418,
              -37.88882566325403
            ],
            [
              144.77501034736633,
              -37.889164352034
            ],
            [
              144.77542877197266,
              -37.88980785642377
            ],
            [
              144.7757613658905,
              -37.89084083855194
            ],
            [
              144.77611541748047,
              -37.89158593141757
            ],
            [
              144.77635145187378,
              -37.89216167983085
            ],
            [
              144.77665185928345,
              -37.892678156193895
            ],
            [
              144.77688789367676,
              -37.89314382849694
            ],
            [
              144.7775423526764,
              -37.893355496751845
            ],
            [
              144.77895855903625,
              -37.893677231333704
            ],
            [
              144.7793984413147,
              -37.89393123132616
            ],
            [
              144.77935552597046,
              -37.89434609609578
            ],
            [
              144.77920532226562,
              -37.89598013254997
            ],
            [
              144.77921605110168,
              -37.897783457101404
            ],
            [
              144.779634475708,
              -37.89823216479691
            ],
            [
              144.77992415428162,
              -37.8980035781995
            ],
            [
              144.7809541225433,
              -37.89780038951694
            ],
            [
              144.78110432624817,
              -37.897461740466234
            ],
            [
              144.78145837783813,
              -37.896792904013765
            ],
            [
              144.7817051410675,
              -37.89618332625727
            ],
            [
              144.78153347969055,
              -37.89544674639967
            ],
            [
              144.78176951408386,
              -37.895057287404235
            ],
            [
              144.78208065032956,
              -37.894388429104076
            ],
            [
              144.78201627731323,
              -37.89375343142347
            ],
            [
              144.7814905643463,
              -37.893253896065445
            ],
            [
              144.78063225746152,
              -37.89265275580174
            ],
            [
              144.77869033813477,
              -37.89144199361073
            ],
            [
              144.77795004844666,
              -37.890713833334
            ],
            [
              144.77732777595517,
              -37.889291359924826
            ],
            [
              144.77694690227509,
              -37.888821429634426
            ],
            [
              144.77558434009552,
              -37.88725073996167
            ],
            [
              144.77485477924347,
              -37.88652253823371
            ],
            [
              144.77422177791595,
              -37.885716004077715
            ],
            [
              144.77395623922348,
              -37.88539635161355
            ],
            [
              144.77361291646957,
              -37.88489675955278
            ],
            [
              144.77339029312134,
              -37.88474434096118
            ],
            [
              144.77261781692505,
              -37.88429978493373
            ],
            [
              144.77236568927765,
              -37.88415371593895
            ],
            [
              144.77186411619186,
              -37.883857343175194
            ],
            [
              144.77117747068405,
              -37.883524980871314
            ],
            [
              144.77033525705338,
              -37.88321590375224
            ],
            [
              144.77015018463135,
              -37.8831989679822
            ],
            [
              144.7698873281479,
              -37.88320108495367
            ],
            [
              144.76838529109952,
              -37.8832074358677
            ],
            [
              144.76731777191162,
              -37.88320320192508
            ],
            [
              144.76630926132202,
              -37.882458024230516
            ],
            [
              144.76570844650269,
              -37.88176364731961
            ],
            [
              144.76519346237183,
              -37.881170881362145
            ],
            [
              144.76522028446198,
              -37.88044685361307
            ],
            [
              144.76528465747833,
              -37.879672009014804
            ],
            [
              144.76584792137143,
              -37.879028416047454
            ],
            [
              144.76622879505157,
              -37.87834670946874
            ],
            [
              144.76640582084656,
              -37.87785553808529
            ],
            [
              144.76643800735474,
              -37.87710183769692
            ],
            [
              144.76574063301086,
              -37.87671228166412
            ],
            [
              144.76557970046997,
              -37.87610677200161
            ],
            [
              144.7651505470276,
              -37.87522602178919
            ],
            [
              144.7647911310196,
              -37.87458238997453
            ],
            [
              144.76378262043,
              -37.873269702396456
            ],
            [
              144.76323008537292,
              -37.87277426261772
            ],
            [
              144.76287066936493,
              -37.8726938062708
            ],
            [
              144.7623771429062,
              -37.872753089903355
            ],
            [
              144.76192116737366,
              -37.87300716207399
            ],
            [
              144.76151883602142,
              -37.87338403417993
            ],
            [
              144.7611916065216,
              -37.873790545750815
            ],
            [
              144.76032793521878,
              -37.874230930754614
            ],
            [
              144.75989878177643,
              -37.874256337501436
            ],
            [
              144.7592657804489,
              -37.87415047599854
            ],
            [
              144.75877225399017,
              -37.87398533175026
            ],
            [
              144.7580909729004,
              -37.87378631126684
            ],
            [
              144.75745260715485,
              -37.873820187131784
            ],
            [
              144.75625097751617,
              -37.87395569043574
            ],
            [
              144.75589692592618,
              -37.874044614343525
            ],
            [
              144.7551727294922,
              -37.87444688782329
            ],
            [
              144.75464165210724,
              -37.8749042065848
            ],
            [
              144.7543627023697,
              -37.875365756900706
            ],
            [
              144.7537887096405,
              -37.87572991382466
            ],
            [
              144.7531235218048,
              -37.8757383825689
            ],
            [
              144.75265681743622,
              -37.87561135130287
            ],
            [
              144.75201845169067,
              -37.87529800657671
            ],
            [
              144.75132644176483,
              -37.87487033121834
            ],
            [
              144.75059151649475,
              -37.87442571558965
            ],
            [
              144.74947035312653,
              -37.87411660028549
            ],
            [
              144.7490358352661,
              -37.874086959023785
            ],
            [
              144.7486442327499,
              -37.87411236582026
            ],
            [
              144.74764108657837,
              -37.87444265337705
            ],
            [
              144.7471582889557,
              -37.874514638930066
            ],
            [
              144.7465467453003,
              -37.87431985433015
            ],
            [
              144.74517345428467,
              -37.873815952649515
            ],
            [
              144.7447282075882,
              -37.87374396641378
            ],
            [
              144.74440097808838,
              -37.873752435386336
            ],
            [
              144.74398255348206,
              -37.87384135953945
            ],
            [
              144.74127888679504,
              -37.87518791216731
            ],
            [
              144.74088728427887,
              -37.87515827133667
            ],
            [
              144.74024891853333,
              -37.87491267542398
            ],
            [
              144.73980903625488,
              -37.874840690259916
            ],
            [
              144.7394496202469,
              -37.87492961309941
            ],
            [
              144.73921895027158,
              -37.87507358318341
            ],
            [
              144.73872542381287,
              -37.87614911549651
            ],
            [
              144.73843574523926,
              -37.87631848923274
            ],
            [
              144.73802268505096,
              -37.87631425489407
            ],
            [
              144.7370034456253,
              -37.87616181854025
            ],
            [
              144.73595201969147,
              -37.8761364124506
            ],
            [
              144.73442316055295,
              -37.87636083260594
            ],
            [
              144.73240613937378,
              -37.876691110081566
            ],
            [
              144.73195552825928,
              -37.87663606393847
            ],
            [
              144.73098993301392,
              -37.876382004283414
            ],
            [
              144.73017990589142,
              -37.8761110063522
            ],
            [
              144.7296541929245,
              -37.87602631929423
            ],
            [
              144.72917139530182,
              -37.876221099381986
            ],
            [
              144.72867250442505,
              -37.87675462481095
            ],
            [
              144.728484749794,
              -37.8771865235184
            ],
            [
              144.72841501235962,
              -37.87770310492102
            ],
            [
              144.7283560037613,
              -37.87868968064791
            ],
            [
              144.72796440124512,
              -37.879028416047454
            ],
            [
              144.72757816314697,
              -37.878943732343615
            ],
            [
              144.72696661949158,
              -37.87882517499467
            ],
            [
              144.72633361816406,
              -37.8788209408001
            ],
            [
              144.72575426101685,
              -37.878943732343615
            ],
            [
              144.72490668296814,
              -37.87925706156149
            ],
            [
              144.72424149513245,
              -37.87956192114279
            ],
            [
              144.72359240055084,
              -37.8795322820722
            ],
            [
              144.72307205200195,
              -37.87929516907816
            ],
            [
              144.72266972064972,
              -37.87896066909217
            ],
            [
              144.7225570678711,
              -37.87865157281798
            ],
            [
              144.72249269485474,
              -37.878067250290115
            ],
            [
              144.72259998321533,
              -37.87746598603848
            ],
            [
              144.72222983837128,
              -37.87616181854025
            ],
            [
              144.72229421138763,
              -37.875933163418026
            ],
            [
              144.72216546535492,
              -37.87561135130287
            ],
            [
              144.72215473651886,
              -37.87411660028549
            ],
            [
              144.7224497795105,
              -37.87361269721456
            ],
            [
              144.7220903635025,
              -37.872668398985105
            ],
            [
              144.72212255001068,
              -37.87250325141447
            ],
            [
              144.72236394882202,
              -37.87180031145967
            ],
            [
              144.72251951694489,
              -37.87115241507977
            ],
            [
              144.72227275371552,
              -37.86997094230753
            ],
            [
              144.72168803215027,
              -37.86910282299891
            ],
            [
              144.72099602222443,
              -37.868509955154266
            ],
            [
              144.72051858901978,
              -37.86831938947682
            ],
            [
              144.71944570541382,
              -37.86831515467839
            ],
            [
              144.71786588430402,
              -37.868372324436656
            ],
            [
              144.7173428535461,
              -37.868279158881904
            ],
            [
              144.7171202301979,
              -37.868509955154266
            ]
          ]
        ]
      }
    },
    {
      "type": "Feature",
      "properties": {},
      "geometry": {
        "type": "Point",
        "coordinates": [
          144.7180523,
          -37.86859676
        ]
      }
    },
    {
      "type": "Feature",
      "properties": {},
      "geometry": {
        "type": "LineString",
        "coordinates": [
          [
            144.71726775169373,
            -37.86844643331654
          ],
          [
            144.71694856882095,
            -37.868198697626184
          ],
          [
            144.7169029712677,
            -37.86823892826503
          ],
          [
            144.71725970506665,
            -37.86850148557906
          ]
        ]
      }
    },
    {
      "type": "Feature",
      "properties": {},
      "geometry": {
        "type": "Point",
        "coordinates": [
          144.7172223,
          -37.868425
        ]
      }
    },
    {
      "type": "Feature",
      "properties": {},
      "geometry": {
        "type": "Point",
        "coordinates": [
          144.7603574,
          -37.87473482
        ]
      }
    },
    {
      "type": "Feature",
      "properties": {},
      "geometry": {
        "type": "Point",
        "coordinates": [
          144.7657889,
          -37.87863463
        ]
      }
    },
    {
      "type": "Feature",
      "properties": {
        "marker-color": "#7e7e7e",
        "marker-size": "medium",
        "marker-symbol": ""
      },
      "geometry": {
        "type": "Point",
        "coordinates": [
          144.76584792137143,
          -37.87842715964179
        ]
      }
    },
    {
      "type": "Feature",
      "properties": {},
      "geometry": {
        "type": "Point",
        "coordinates": [
          144.76596057415009,
          -37.878698149051885
        ]
      }
    },
    {
      "type": "Feature",
      "properties": {},
      "geometry": {
        "type": "Point",
        "coordinates": [
          144.76603031158447,
          -37.87855418605191
        ]
      }
    },
    {
      "type": "Feature",
      "properties": {},
      "geometry": {
        "type": "Point",
        "coordinates": [
          144.7661054134369,
          -37.87840598855213
        ]
      }
    },
    {
      "type": "Feature",
      "properties": {},
      "geometry": {
        "type": "Point",
        "coordinates": [
          144.76617515087128,
          -37.87826202498112
        ]
      }
    },
    {
      "type": "Feature",
      "properties": {},
      "geometry": {
        "type": "Point",
        "coordinates": [
          144.75585132837296,
          -37.87341155847167
        ]
      }
    }
  ]
}